[1,["f2D2Kasszih2AxHoVDVpOI","e9x0a96K+YKh+a1/1IMrf6","25RWToxeEg4ZYfrN33rT7a","f7DtOxXCtZDGMuBuQnRKCe","e6CDf2MVgfNCLbmTNXGi7w","682zXPJZ2g8U5APlzD8yNo","996tKBA/NRLJcZsH24A+5m","f5jNCO3JS/gafCfxe7DbUn","03VtjPGCZm0a9uJSLhlMhn","c73NVw1uJMb2XPZ/GZ8Pe1","3b9T8mPVNrirannHqoI0EZ","34A6KoloYD0eOOToxE9Z43","39RtwfePBps6FlXqM12TJz","7ejq1u6Zaf1G3FeuZkTjDz","64jnTpWAILHSFwKKth+krh","8ez0bB1goDYJDzWSeg+Oxx","b1V5mUvVS0KdBSeAHhK9u0","16yKSgs8zDYSGbOLP1vPpq","d9hWuRqMVCUH5DaMTYOmm0","fcdTc5OGLj6MgoWA1O66fJ","39F+Ed/eOKJjWlU/ZtSh+2","2aPUtpxyQmfsC7i8f15waE","e9WMrJAzWJfXs3p/FT3ync","13zOS+p1IrmaPNhrLleJWj","eadfUDFhXVOXq9UyQUFYUu","4cIYzmCHCZxKzsGIB64GMH"],["_textureSetter"],["cc.SpriteFrame",["cc.AnimationClip",["_name","_duration","sample","wrapMode","curveData"],-2]],[[1,0,1,2,3,4,6]],[[[{"name":"fram1","rect":[0,0,625,14],"offset":[0,0],"originalSize":[625,14],"capInsets":[0,0,0,0]}],[0],0,[0],[0],[0]],[[{"name":"Pay_buy","rect":[0,0,211,69],"offset":[0,0],"originalSize":[211,69],"capInsets":[0,0,0,0]}],[0],0,[0],[0],[1]],[[{"name":"gou","rect":[0,0,110,70],"offset":[0,0],"originalSize":[110,70],"capInsets":[0,0,0,0]}],[0],0,[0],[0],[2]],[[{"name":"bgItem3","rect":[0,0,926,118],"offset":[0,0],"originalSize":[926,118],"capInsets":[0,0,0,0]}],[0],0,[0],[0],[3]],[[{"name":"title","rect":[0,0,407,54],"offset":[0,0],"originalSize":[407,54],"capInsets":[0,0,0,0]}],[0],0,[0],[0],[4]],[[{"name":"roundlight","rect":[0,0,228,225],"offset":[0,0],"originalSize":[228,225],"capInsets":[0,0,0,0]}],[0],0,[0],[0],[5]],[[{"name":"Rd_d_BG01","rect":[0,0,809,537],"offset":[0,0],"originalSize":[809,537],"capInsets":[50,50,50,50]}],[0],0,[0],[0],[6]],[[{"name":"Charge value_ USD","rect":[0,0,662,65],"offset":[0,0],"originalSize":[662,65],"capInsets":[0,0,0,0]}],[0],0,[0],[0],[7]],[[{"name":"nextStep","rect":[0,0,390,81],"offset":[0,0],"originalSize":[390,81],"capInsets":[0,0,0,0]}],[0],0,[0],[0],[8]],[[{"name":"Get","rect":[0,0,163,49],"offset":[0,0],"originalSize":[163,49],"capInsets":[0,0,0,0]}],[0],0,[0],[0],[9]],[[{"name":"？","rect":[0,0,49,48],"offset":[0,0],"originalSize":[49,48],"capInsets":[0,0,0,0]}],[0],0,[0],[0],[10]],[[{"name":"title","rect":[0,0,745,154],"offset":[0,0],"originalSize":[745,154],"capInsets":[0,0,0,0]}],[0],0,[0],[0],[11]],[[[0,"popwaitAnim",1.5,40,2,{"paths":{"roundlight":{"props":{"angle":[{"frame":0,"value":0},{"frame":1.5,"value":-360}]}}}}]],0,0,[],[],[]],[[{"name":"×","rect":[0,0,86,90],"offset":[0,0],"originalSize":[86,90],"capInsets":[0,0,0,0]}],[0],0,[0],[0],[12]],[[{"name":"图层 4","rect":[0,0,121,71],"offset":[0,0],"originalSize":[121,71],"capInsets":[0,0,0,0]}],[0],0,[0],[0],[13]],[[{"name":"okbtn","rect":[0,0,237,65],"offset":[0,0],"originalSize":[237,65],"capInsets":[0,0,0,0]}],[0],0,[0],[0],[14]],[[{"name":"Notice_Close","rect":[0,0,46,44],"offset":[0,0],"originalSize":[46,44],"capInsets":[0,0,0,0]}],[0],0,[0],[0],[15]],[[{"name":"Pay_cancel","rect":[0,0,211,69],"offset":[0,0],"originalSize":[211,69],"capInsets":[0,0,0,0]}],[0],0,[0],[0],[16]],[[{"name":"qudao_on","rect":[0,0,179,108],"offset":[0,0],"originalSize":[179,108],"capInsets":[0,0,0,0]}],[0],0,[0],[0],[17]],[[{"name":"图层 7","rect":[0,0,1920,1080],"offset":[0,0],"originalSize":[1920,1080],"capInsets":[0,0,0,0]}],[0],0,[0],[0],[18]],[[{"name":"Player ID","rect":[0,0,349,65],"offset":[0,0],"originalSize":[349,65],"capInsets":[0,0,0,0]}],[0],0,[0],[0],[19]],[[{"name":"cashPay","rect":[0,0,193,42],"offset":[0,0],"originalSize":[193,42],"capInsets":[0,0,0,0]}],[0],0,[0],[0],[20]],[[{"name":"tip_tittle","rect":[0,0,483,68],"offset":[0,0],"originalSize":[483,68],"capInsets":[0,0,0,0]}],[0],0,[0],[0],[21]],[[{"name":"frame","rect":[0,0,1085,620],"offset":[0,0],"originalSize":[1085,620],"capInsets":[60,50,60,50]}],[0],0,[0],[0],[22]],[[{"name":"fram1","rect":[0,0,1011,369],"offset":[0,0],"originalSize":[1011,369],"capInsets":[0,0,0,0]}],[0],0,[0],[0],[23]],[[{"name":"矩形 3","rect":[0,0,49,48],"offset":[0,0],"originalSize":[49,48],"capInsets":[0,0,0,0]}],[0],0,[0],[0],[24]],[[{"name":"qudao_off","rect":[0,0,179,108],"offset":[0,0],"originalSize":[179,108],"capInsets":[0,0,0,0]}],[0],0,[0],[0],[25]]]]