[1,["9fRgkRYTRCTpAqs6v3ByNR"],["_textureSetter"],["cc.SpriteFrame"],0,[[[{"name":"22_05","rect":[0,536,272,302],"offset":[0,0],"originalSize":[272,302],"capInsets":[0,0,0,0]}],[0],0,[0],[0],[0]],[[{"name":"22_06","rect":[272,536,272,302],"offset":[0,0],"originalSize":[272,302],"capInsets":[0,0,0,0]}],[0],0,[0],[0],[0]],[[{"name":"22_04","rect":[242,310,267,107],"offset":[0,0],"originalSize":[267,107],"capInsets":[0,0,0,0]}],[0],0,[0],[0],[0]],[[{"name":"22_02","rect":[0,310,242,226],"offset":[0,0],"originalSize":[242,226],"capInsets":[0,0,0,0]}],[0],0,[0],[0],[0]],[[{"name":"22_07","rect":[544,536,272,302],"offset":[0,0],"originalSize":[272,302],"capInsets":[0,0,0,0]}],[0],0,[0],[0],[0]],[[{"name":"22_03","rect":[509,310,268,109],"offset":[0,0],"originalSize":[268,109],"capInsets":[0,0,0,0]}],[0],0,[0],[0],[0]],[[{"name":"22_01","rect":[0,0,168,268],"offset":[0,0],"originalSize":[168,268],"capInsets":[0,0,0,0]}],[0],0,[0],[0],[0]]]]