[1,["81Y40JPLNMHbnZQ/LocyZJ"],["_textureSetter"],["cc.SpriteFrame"],0,[[[{"name":"Sprite_16","rect":[167,396,227,163],"offset":[0,0],"originalSize":[227,163],"rotated":1,"capInsets":[0,0,0,0]}],[0],0,[0],[0],[0]],[[{"name":"Sprite_9","rect":[2,2,227,163],"offset":[0,0],"originalSize":[227,163],"capInsets":[0,0,0,0]}],[0],0,[0],[0],[0]],[[{"name":"Sprite_15","rect":[167,625,227,163],"offset":[0,0],"originalSize":[227,163],"rotated":1,"capInsets":[0,0,0,0]}],[0],0,[0],[0],[0]],[[{"name":"Sprite_12","rect":[689,167,227,163],"offset":[0,0],"originalSize":[227,163],"capInsets":[0,0,0,0]}],[0],0,[0],[0],[0]],[[{"name":"Sprite_17","rect":[167,167,227,163],"offset":[0,0],"originalSize":[227,163],"rotated":1,"capInsets":[0,0,0,0]}],[0],0,[0],[0],[0]],[[{"name":"Sprite_4","rect":[2,396,227,163],"offset":[0,0],"originalSize":[227,163],"rotated":1,"capInsets":[0,0,0,0]}],[0],0,[0],[0],[0]],[[{"name":"Sprite_7","rect":[460,2,227,163],"offset":[0,0],"originalSize":[227,163],"capInsets":[0,0,0,0]}],[0],0,[0],[0],[0]],[[{"name":"Sprite_1","rect":[460,790,227,163],"offset":[0,0],"originalSize":[227,163],"rotated":1,"capInsets":[0,0,0,0]}],[0],0,[0],[0],[0]],[[{"name":"Sprite_2","rect":[2,854,227,163],"offset":[0,0],"originalSize":[227,163],"capInsets":[0,0,0,0]}],[0],0,[0],[0],[0]],[[{"name":"Sprite_10","rect":[332,561,227,163],"offset":[0,0],"originalSize":[227,163],"rotated":1,"capInsets":[0,0,0,0]}],[0],0,[0],[0],[0]],[[{"name":"Sprite_14","rect":[231,854,227,163],"offset":[0,0],"originalSize":[227,163],"capInsets":[0,0,0,0]}],[0],0,[0],[0],[0]],[[{"name":"Sprite_11","rect":[332,332,227,163],"offset":[0,0],"originalSize":[227,163],"rotated":1,"capInsets":[0,0,0,0]}],[0],0,[0],[0],[0]],[[{"name":"Sprite_3","rect":[2,625,227,163],"offset":[0,0],"originalSize":[227,163],"rotated":1,"capInsets":[0,0,0,0]}],[0],0,[0],[0],[0]],[[{"name":"Sprite_5","rect":[2,167,227,163],"offset":[0,0],"originalSize":[227,163],"rotated":1,"capInsets":[0,0,0,0]}],[0],0,[0],[0],[0]],[[{"name":"Sprite_13","rect":[460,167,227,163],"offset":[0,0],"originalSize":[227,163],"capInsets":[0,0,0,0]}],[0],0,[0],[0],[0]],[[{"name":"Sprite_8","rect":[231,2,227,163],"offset":[0,0],"originalSize":[227,163],"capInsets":[0,0,0,0]}],[0],0,[0],[0],[0]],[[{"name":"Sprite_6","rect":[689,2,227,163],"offset":[0,0],"originalSize":[227,163],"capInsets":[0,0,0,0]}],[0],0,[0],[0],[0]]]]