[1,["3foW18VHhKmq6x8B+GzwQC","06aqKrgrZMpZmdtx6nH2Td"],["value","_textureSetter"],["cc.SpriteFrame",["cc.AnimationClip",["_name","_duration","sample","curveData"],0,11]],[[1,0,1,2,3,4]],[[[[0,"Anim_FSMinerExitLeft_2",2,1,[{},"paths",11,[{},"MinerExit",11,[{"props":{"active":[{"frame":0,"value":true}],"position":[{"frame":0,"value":[-950.417,-300,0]},{"frame":2,"value":[964.848,-300,0]}]}},"comps",11,[{},"cc.Sprite",11,[{},"spriteFrame",12,[[[{"frame":0},"value",6,0]],11]]]]]]]],0,0,[0],[0],[0]],[[{"name":"MinerExit_Left","rect":[0,0,293,372],"offset":[0,0],"originalSize":[293,372],"capInsets":[0,0,0,0]}],[0],0,[0],[1],[1]]]]