[1,["a7xjv3+kJJvo6pxeOSP0wp","b7vL4RJQhE45A7aDqy7whH","5ac0hhpGhOBbxeMOpmGqdJ","b5o2Iq0A9NKa4EPPIE18Yx","4f09VqaD9NZ4U4dnC/LA0g","03K+v+mPBIn6Ps9vrxRVOp","8crTKSlCxNZbCCSYbEWwyW","52ASt/CZVBMIxZUy31mqpi","50i8hDGTZM3aWPjHp4Ohrq","47cRta++pLm6C8aeFkCQni","4aKl/P7KJBIILfz/CKEvOr","ae4MtCyt5DVJq7+reYnuc7","716drAPtZEGIYQymWEDz4T","03XW7106VAW6Y85as6JZXc","e5Z/kI2AVHFonl/8iPkkGS","59BEsghyRMcKc1FP9scLp9","0f2+RF0nxC4pkI/cjgTWQZ","73v7KAVTRH+7nYoyEuYL5r","2b+r2ynJRMmYRHzMk3+Zmg","65s7i1WRpHDr4D7tsyjAuz","63MhAKRJpBELT/8K+iPLSt","5cDRSZPG9NnoDhVxaQ5jTm","45wIOYKYFLpKb9izvxY7ve","dbKGDwyF9NibUfGrOw9/ZI"],["value"],[["cc.AnimationClip",["_name","_duration","sample","speed","wrapMode","curveData"],-2,11]],[[0,0,1,2,3,4,5,6]],[[0,"Anim_Lantem_2",1.2,20,0.2,2,[{},"comps",11,[{},"cc.Sprite",11,[{},"spriteFrame",12,[[[{"frame":0},"value",6,0],[{"frame":0.05},"value",6,1],[{"frame":0.1},"value",6,2],[{"frame":0.15},"value",6,3],[{"frame":0.2},"value",6,4],[{"frame":0.25},"value",6,5],[{"frame":0.3},"value",6,6],[{"frame":0.35},"value",6,7],[{"frame":0.4},"value",6,8],[{"frame":0.45},"value",6,9],[{"frame":0.5},"value",6,10],[{"frame":0.55},"value",6,11],[{"frame":0.6},"value",6,12],[{"frame":0.65},"value",6,13],[{"frame":0.7},"value",6,14],[{"frame":0.75},"value",6,15],[{"frame":0.8},"value",6,16],[{"frame":0.85},"value",6,17],[{"frame":0.9},"value",6,18],[{"frame":0.95},"value",6,19],[{"frame":1},"value",6,20],[{"frame":1.05},"value",6,21],[{"frame":1.1},"value",6,22],[{"frame":1.15},"value",6,23]],11,11,11,11,11,11,11,11,11,11,11,11,11,11,11,11,11,11,11,11,11,11,11,11]]]]]],0,0,[0,0,0,0,0,0,0,0,0,0,0,0,0,0,0,0,0,0,0,0,0,0,0,0],[0,0,0,0,0,0,0,0,0,0,0,0,0,0,0,0,0,0,0,0,0,0,0,0],[0,1,2,3,4,5,6,7,8,9,10,11,12,13,14,15,16,17,18,19,20,21,22,23]]