[1,["ecpdLyjvZBwrvm+cedCcQy","b2LU9LVkdJEoLSS4NZdf6V","2c7uCLDndI744oTILZD5v6","6dvp7RR0JIeopj0ZzNclhM","16VcCoZk9EY6rr8/hUh+nK","1btVnK1QlI04XC4Ww4GjhL","23uNXOQjRA8rR8pIBo1lyU","d7wiTt1pdHmZz/eN8KTugE","6fdOikipFGd4ECBguRztjm","b0b/SpIxpEyqXBhbyDpMBb","83X7YHEnBHQ6h/7xHMADkt","9e3/p38bVMGIpByVbLpis9","2fqkQ/7LZHiKx3z7fRfvKm","0dIy8ZxIhAKaocHGrJy7/d"],["node","_spriteFrame","_defaultClip","spriteFrame","_textureSetter","root","math","hit","ma","flyParent","fly","littleBoom","boom","data","_N$file"],[["cc.Node",["_name","_active","_opacity","_prefab","_components","_parent","_contentSize","_trs","_children","_anchorPoint"],0,4,9,1,5,7,2,5],["cc.PrefabInfo",["fileId","root"],2,1],["cc.Animation",["playOnLoad","node","_clips","_defaultClip"],2,1,3,6],"cc.SpriteFrame",["cc.LabelAtlas",["_name","fontSize","_fntConfig"],0],["cc.Prefab",["_name"],2],["cc.Node",["_name","_parent","_components","_prefab","_contentSize","_anchorPoint","_trs"],2,1,2,4,5,5,7],["cdee7K6Z0FLtJnXHZeqf9Aa",["node","boom","littleBoom","fly","flyParent","ma","hit","math"],3,1,1,1,1,1,1,1,1],["cc.Sprite",["node","_materials","_spriteFrame"],3,1,3,6],["cc.Label",["_string","_fontSize","_isSystemFontUsed","_N$verticalAlign","node","_materials"],-1,1,3]],[[1,0,1,2],[8,0,1,2,1],[0,0,1,5,4,3,6,7,3],[2,1,2,3,1],[2,0,1,2,3,2],[4,0,1,2,4],[5,0,2],[0,0,8,4,3,2],[0,0,1,5,8,4,3,6,9,7,3],[0,0,1,2,5,4,3,6,7,4],[0,0,5,3,2],[6,0,1,2,3,4,5,6,2],[7,0,1,2,3,4,5,6,7,1],[1,1,1],[9,0,1,2,3,4,5,5]],[[[[5,"LabelAtlasNumber1",39.6,{"commonHeight":45,"fontSize":39,"atlasName":"number1","fontDefDictionary":{"46":{"xOffset":0,"yOffset":0,"xAdvance":38,"rect":{"x":0,"y":0,"width":38,"height":45}},"47":{"xOffset":0,"yOffset":0,"xAdvance":38,"rect":{"x":38,"y":0,"width":38,"height":45}},"48":{"xOffset":0,"yOffset":0,"xAdvance":38,"rect":{"x":76,"y":0,"width":38,"height":45}},"49":{"xOffset":0,"yOffset":0,"xAdvance":38,"rect":{"x":114,"y":0,"width":38,"height":45}},"50":{"xOffset":0,"yOffset":0,"xAdvance":38,"rect":{"x":152,"y":0,"width":38,"height":45}},"51":{"xOffset":0,"yOffset":0,"xAdvance":38,"rect":{"x":190,"y":0,"width":38,"height":45}},"52":{"xOffset":0,"yOffset":0,"xAdvance":38,"rect":{"x":228,"y":0,"width":38,"height":45}},"53":{"xOffset":0,"yOffset":0,"xAdvance":38,"rect":{"x":266,"y":0,"width":38,"height":45}},"54":{"xOffset":0,"yOffset":0,"xAdvance":38,"rect":{"x":304,"y":0,"width":38,"height":45}},"55":{"xOffset":0,"yOffset":0,"xAdvance":38,"rect":{"x":342,"y":0,"width":38,"height":45}},"56":{"xOffset":0,"yOffset":0,"xAdvance":38,"rect":{"x":380,"y":0,"width":38,"height":45}},"57":{"xOffset":0,"yOffset":0,"xAdvance":38,"rect":{"x":418,"y":0,"width":38,"height":45}}},"kerningDict":{}}]],0,0,[0],[3],[6]],[[{"name":"number1","rect":[0,0,456,45],"offset":[0,0],"originalSize":[456,45],"capInsets":[0,0,0,0]}],[3],0,[0],[4],[7]],[[[6,"duJiaoEffect"],[7,"duJiaoEffect",[-10,-11,-12,-13,-14,-15],[[12,-9,-8,-7,-6,-5,-4,-3,-2]],[13,-1]],[8,"hit",false,1,[-18],[[1,-16,[13],14],[4,true,-17,[16],15]],[0,"f8fEagZj5ME529KXJ8ROh0",1],[5,299,153],[0,0.5,0],[-76.765,0,0,0,0,0,1,2,2,1]],[2,"boom",false,1,[[1,-19,[0],1],[3,-20,[3],2]],[0,"49g4Wii2tO+bU0RrrZmDSv",1],[5,379,214],[0,0,0,0,0,0,1,3.6,3.6,1]],[2,"fly",false,1,[[1,-21,[4],5],[3,-22,[7],6]],[0,"75IfseAu5GtqxdSv6n/l4N",1],[5,326,183],[0,0,0,0,0,0,1,5,5,1]],[2,"ma",false,1,[[1,-23,[8],9],[4,true,-24,[11],10]],[0,"9avGeCkbpOSoi/w6z5WDE+",1],[5,230,251],[0,0,0,0,0,0,1,2,2,1]],[9,"littleBoom",false,0,1,[[1,-25,[17],18],[3,-26,[20],19]],[0,"3fqg9+XFVExpyJKEWcFgsP",1],[5,238,234],[0,0,0,0,0,0,1,2,2,1]],[10,"flyParent",1,[0,"dcE6HXyqZHh5janA41+h7S",1]],[11,"math",2,[-27],[0,"c5gkG+Y8lPgavpSUvQvAjB",1],[5,125.64,40],[0,0,0.5],[140.946,58.898,0,0,0,0,1,1,1,1]],[14,"99",70,false,1,8,[12]]],0,[0,5,1,0,6,9,0,7,2,0,8,5,0,9,7,0,10,4,0,11,6,0,12,3,0,0,1,0,-1,3,0,-2,4,0,-3,7,0,-4,5,0,-5,2,0,-6,6,0,0,2,0,0,2,0,-1,8,0,0,3,0,0,3,0,0,4,0,0,4,0,0,5,0,0,5,0,0,6,0,0,6,0,-1,9,0,13,1,27],[0,0,0,0,0,0,0,0,0,0,0,0,0,0,0,0,0,0,0,0,0,9],[-1,1,2,-1,-1,1,2,-1,-1,1,2,-1,-1,-1,1,2,-1,-1,1,2,-1,14],[0,8,1,1,0,9,2,2,0,10,3,3,0,0,11,4,4,0,12,5,5,13]]]]