[1,["d5xsmpkqZBWJ1WthG9HOf+","75xBeqS+5HT4od/rQ2xAz3","778SspB6hBx7w43iUh0PTo","07cdBt7TZAFIvzoXLAGV8b","e86eS7KoVBErBnJtaG8ts/","6d71OAPS1J44rwM/d5i4I6"],["value"],[["cc.AnimationClip",["_name","_duration","sample","wrapMode","curveData"],-1,11]],[[0,0,1,2,3,4,5]],[[0,"die",0.6,10,2,[{},"comps",11,[{},"cc.Sprite",11,[{},"spriteFrame",12,[[[{"frame":0},"value",6,0],[{"frame":0.1},"value",6,1],[{"frame":0.2},"value",6,2],[{"frame":0.3},"value",6,3],[{"frame":0.4},"value",6,4],[{"frame":0.5},"value",6,5]],11,11,11,11,11,11]]]]]],0,0,[0,0,0,0,0,0],[0,0,0,0,0,0],[0,1,2,3,4,5]]