[1,["cbBHhIv1tCb5/r5euiqFAd","71D2GEkG5EDbn1j8KOjC/t","a4iUeVBPdDH5DiPwLiPc59","acH8EDG8lDnIcw+JVFsZGa","2ftXdo5yxCDLZ4JxTURAPL","faU82l871FconcpQxfAQzS","dcKXWK9VFEq7RlYoBJTbMR","156qtXGC5C44pM7gt7GXG0","39fUO60ZNPx56nc/KWX9NP","ffmqtpG9VKYo0mlXDOnNS0","94znyxVIBKjo072HD6T5b7","88+niURqFMrIfKa+OTA9ez","51MYDyWbNG5L7YklEkkud/","b3Jvu805RKGrTwOyTDuw7M","1bvhZEK3BLsYACqF7vB/tD","88pQXNn2hGN7JuQLj21fz3"],["_textureSetter","GoldBox_Crocodile_001","GoldBox_Crocodile_002","GoldBox_Crocodile_003","GoldBox_Crocodile_004","GoldBox_Crocodile_005","GoldBox_Crocodile_006","GoldBox_Crocodile_007","GoldBox_Crocodile_008","GoldBox_Crocodile_009","GoldBox_Crocodile_010","GoldBox_Crocodile_011","GoldBox_Crocodile_012","GoldBox_Crocodile_013","GoldBox_Crocodile_014","GoldBox_Crocodile_015"],["cc.SpriteFrame",["cc.SpriteAtlas",["_name","_spriteFrames"],2,11]],[[1,0,1,2]],[[[{"name":"GoldBox_Crocodile_007","rect":[2,2,119,167],"offset":[0,0],"originalSize":[119,167],"capInsets":[0,0,0,0]}],[0],0,[0],[0],[0]],[[{"name":"GoldBox_Crocodile_014","rect":[2,340,108,167],"offset":[0,0],"originalSize":[108,167],"capInsets":[0,0,0,0]}],[0],0,[0],[0],[0]],[[{"name":"GoldBox_Crocodile_004","rect":[123,2,103,167],"offset":[0,0],"originalSize":[103,167],"capInsets":[0,0,0,0]}],[0],0,[0],[0],[0]],[[{"name":"GoldBox_Crocodile_008","rect":[457,337,133,165],"offset":[0,0],"originalSize":[133,165],"capInsets":[0,0,0,0]}],[0],0,[0],[0],[0]],[[{"name":"GoldBox_Crocodile_012","rect":[226,171,102,167],"offset":[0,0],"originalSize":[102,167],"capInsets":[0,0,0,0]}],[0],0,[0],[0],[0]],[[[0,"eyugold.plist",[{},"GoldBox_Crocodile_001",6,0,"GoldBox_Crocodile_002",6,1,"GoldBox_Crocodile_003",6,2,"GoldBox_Crocodile_004",6,3,"GoldBox_Crocodile_005",6,4,"GoldBox_Crocodile_006",6,5,"GoldBox_Crocodile_007",6,6,"GoldBox_Crocodile_008",6,7,"GoldBox_Crocodile_009",6,8,"GoldBox_Crocodile_010",6,9,"GoldBox_Crocodile_011",6,10,"GoldBox_Crocodile_012",6,11,"GoldBox_Crocodile_013",6,12,"GoldBox_Crocodile_014",6,13,"GoldBox_Crocodile_015",6,14]]],0,0,[0,0,0,0,0,0,0,0,0,0,0,0,0,0,0],[1,2,3,4,5,6,7,8,9,10,11,12,13,14,15],[1,2,3,4,5,6,7,8,9,10,11,12,13,14,15]],[[{"name":"GoldBox_Crocodile_001","rect":[456,170,136,165],"offset":[0,0],"originalSize":[136,165],"capInsets":[0,0,0,0]}],[0],0,[0],[0],[0]],[[{"name":"GoldBox_Crocodile_015","rect":[330,170,124,166],"offset":[0,0],"originalSize":[124,166],"capInsets":[0,0,0,0]}],[0],0,[0],[0],[0]],[[{"name":"GoldBox_Crocodile_011","rect":[112,340,108,167],"offset":[0,0],"originalSize":[108,167],"capInsets":[0,0,0,0]}],[0],0,[0],[0],[0]],[[{"name":"GoldBox_Crocodile_010","rect":[330,2,125,166],"offset":[0,0],"originalSize":[125,166],"capInsets":[0,0,0,0]}],[0],0,[0],[0],[0]],[[{"name":"GoldBox_Crocodile_002","rect":[326,340,129,166],"offset":[0,0],"originalSize":[129,166],"capInsets":[0,0,0,0]}],[0],0,[0],[0],[0]],[[{"name":"GoldBox_Crocodile_003","rect":[2,171,114,167],"offset":[0,0],"originalSize":[114,167],"capInsets":[0,0,0,0]}],[0],0,[0],[0],[0]],[[{"name":"GoldBox_Crocodile_013","rect":[222,340,102,167],"offset":[0,0],"originalSize":[102,167],"capInsets":[0,0,0,0]}],[0],0,[0],[0],[0]],[[{"name":"GoldBox_Crocodile_006","rect":[118,171,106,167],"offset":[0,0],"originalSize":[106,167],"capInsets":[0,0,0,0]}],[0],0,[0],[0],[0]],[[{"name":"GoldBox_Crocodile_005","rect":[228,2,100,167],"offset":[0,0],"originalSize":[100,167],"capInsets":[0,0,0,0]}],[0],0,[0],[0],[0]],[[{"name":"GoldBox_Crocodile_009","rect":[457,2,135,165],"offset":[0,0],"originalSize":[135,165],"capInsets":[0,0,0,0]}],[0],0,[0],[0],[0]]]]